{
    "horario": ["16:00", "16:15", "16:30", "16:45",
      "17:00", "17:15", "17:30", "17:45", 
      "18:00", "18:15", "18:30", "18:45", 
      "19:00", "19:15", "19:30", "18.45", 
      "20:00", "20:15", "20:30", "120:45", 
      "21:00", "21:15", "21:30", "21:45", 
      "22:00", "22:15", "22:30", "22:45", 
      "23:00", "23:15", "23:30", "23:45", 
      "00:00", "00:15", "00:30", "00:45"],
    "paradas": [
        {
            "_lat": "43.3529594",
            "_lon": "-1.7980396",
            "lines": ["H-6"],
            "name": "Amute, 20280 Amute-Kosta, Guipúzcoa"
          },
          {
            "_lat": "43.360432",
            "_lon": "-1.79535",
            "lines": ["H-6"],
            "name": "S.engrazia"
          },
          {
            "_lat": "43.3617477",
            "_lon": "-1.789898",
            "lines": ["H-6"],
            "name": "S. Arana"
          },
          {
            "_lat": "43.365995",
            "_lon": "-1.792685",
            "lines": ["H-6"],
            "name": "Correos"
          },
          {
            "_lat": "43.368008",
            "_lon": "-1.795706",
            "lines": ["H-6"],
            "name": "Madalengai"
          },
          {
            "_lat": "43.3720673",
            "_lon": "-1.794294",
            "lines": ["H-6"],
            "name": "Foru Kalea"
          },
          {
            "_lat": "43.369383",
            "_lon": "-1.793741",
            "lines": ["H-6"],
            "name": "Itsasargi"
          },
          {
            "_lat": "43.35688",
            "_lon": "-1.7946",
            "lines": ["H-6"],
            "name": "Terminal 1"
          },
          {
            "_lat": "43.3529419",
            "_lon": "-1.7980422",
            "lines": ["H-6"],
            "name": "Kosta Kalea, 49, 20280 Amute-Kosta, Gipuzkoa"
          }
    ],
    "ruta": {
        "idRuta": "H - 25",
        "puntos": [
            {
                "_lat": "43.35296",
                "_lon": "-1.79804"
              },
              {
                "_lat": "43.35298",
                "_lon": "-1.79803"
              },
              {
                "_lat": "43.35303",
                "_lon": "-1.79802"
              },
              {
                "_lat": "43.35309",
                "_lon": "-1.798"
              },
              {
                "_lat": "43.35316",
                "_lon": "-1.79799"
              },
              {
                "_lat": "43.35323",
                "_lon": "-1.79799"
              },
              {
                "_lat": "43.3533",
                "_lon": "-1.79799"
              },
              {
                "_lat": "43.35338",
                "_lon": "-1.798"
              },
              {
                "_lat": "43.35365",
                "_lon": "-1.79804"
              },
              {
                "_lat": "43.35412",
                "_lon": "-1.79813"
              },
              {
                "_lat": "43.35443",
                "_lon": "-1.79816"
              },
              {
                "_lat": "43.35464",
                "_lon": "-1.79818"
              },
              {
                "_lat": "43.35477",
                "_lon": "-1.79818"
              },
              {
                "_lat": "43.35498",
                "_lon": "-1.79817"
              },
              {
                "_lat": "43.35507",
                "_lon": "-1.79816"
              },
              {
                "_lat": "43.35513",
                "_lon": "-1.79814"
              },
              {
                "_lat": "43.3553",
                "_lon": "-1.79808"
              },
              {
                "_lat": "43.3555",
                "_lon": "-1.798"
              },
              {
                "_lat": "43.3558",
                "_lon": "-1.79788"
              },
              {
                "_lat": "43.35599",
                "_lon": "-1.7978"
              },
              {
                "_lat": "43.35626",
                "_lon": "-1.79767"
              },
              {
                "_lat": "43.35655",
                "_lon": "-1.79753"
              },
              {
                "_lat": "43.35665",
                "_lon": "-1.79748"
              },
              {
                "_lat": "43.35686",
                "_lon": "-1.79739"
              },
              {
                "_lat": "43.35709",
                "_lon": "-1.7973"
              },
              {
                "_lat": "43.35723",
                "_lon": "-1.79725"
              },
              {
                "_lat": "43.35744",
                "_lon": "-1.7972"
              },
              {
                "_lat": "43.3576",
                "_lon": "-1.79717"
              },
              {
                "_lat": "43.35787",
                "_lon": "-1.79711"
              },
              {
                "_lat": "43.35795",
                "_lon": "-1.79709"
              },
              {
                "_lat": "43.35848",
                "_lon": "-1.79696"
              },
              {
                "_lat": "43.35856",
                "_lon": "-1.79694"
              },
              {
                "_lat": "43.35861",
                "_lon": "-1.79692"
              },
              {
                "_lat": "43.35876",
                "_lon": "-1.79686"
              },
              {
                "_lat": "43.35902",
                "_lon": "-1.79673"
              },
              {
                "_lat": "43.35902",
                "_lon": "-1.79673"
              },
              {
                "_lat": "43.35944",
                "_lon": "-1.79632"
              },
              {
                "_lat": "43.35952",
                "_lon": "-1.79624"
              },
              {
                "_lat": "43.35956",
                "_lon": "-1.7962"
              },
              {
                "_lat": "43.35959",
                "_lon": "-1.79615"
              },
              {
                "_lat": "43.35972",
                "_lon": "-1.79597"
              },
              {
                "_lat": "43.35983",
                "_lon": "-1.79581"
              },
              {
                "_lat": "43.35986",
                "_lon": "-1.79576"
              },
              {
                "_lat": "43.35988",
                "_lon": "-1.79573"
              },
              {
                "_lat": "43.35991",
                "_lon": "-1.79569"
              },
              {
                "_lat": "43.35993",
                "_lon": "-1.79567"
              },
              {
                "_lat": "43.35995",
                "_lon": "-1.79565"
              },
              {
                "_lat": "43.35997",
                "_lon": "-1.79562"
              },
              {
                "_lat": "43.36001",
                "_lon": "-1.7956"
              },
              {
                "_lat": "43.36006",
                "_lon": "-1.79557"
              },
              {
                "_lat": "43.36013",
                "_lon": "-1.79555"
              },
              {
                "_lat": "43.36028",
                "_lon": "-1.79551"
              },
              {
                "_lat": "43.36036",
                "_lon": "-1.79549"
              },
              {
                "_lat": "43.36039",
                "_lon": "-1.79547"
              },
              {
                "_lat": "43.3604",
                "_lon": "-1.79546"
              },
              {
                "_lat": "43.36041",
                "_lon": "-1.79545"
              },
              {
                "_lat": "43.36045",
                "_lon": "-1.79537"
              },
              {
                "_lat": "43.36045",
                "_lon": "-1.79537"
              },
              {
                "_lat": "43.36046",
                "_lon": "-1.79535"
              },
              {
                "_lat": "43.3605",
                "_lon": "-1.79522"
              },
              {
                "_lat": "43.36054",
                "_lon": "-1.79512"
              },
              {
                "_lat": "43.36055",
                "_lon": "-1.79509"
              },
              {
                "_lat": "43.36057",
                "_lon": "-1.79506"
              },
              {
                "_lat": "43.36061",
                "_lon": "-1.79501"
              },
              {
                "_lat": "43.36061",
                "_lon": "-1.79501"
              },
              {
                "_lat": "43.36063",
                "_lon": "-1.79502"
              },
              {
                "_lat": "43.36065",
                "_lon": "-1.79503"
              },
              {
                "_lat": "43.36069",
                "_lon": "-1.79504"
              },
              {
                "_lat": "43.36073",
                "_lon": "-1.79505"
              },
              {
                "_lat": "43.36075",
                "_lon": "-1.79505"
              },
              {
                "_lat": "43.36079",
                "_lon": "-1.79505"
              },
              {
                "_lat": "43.36081",
                "_lon": "-1.79505"
              },
              {
                "_lat": "43.36087",
                "_lon": "-1.79504"
              },
              {
                "_lat": "43.36091",
                "_lon": "-1.79503"
              },
              {
                "_lat": "43.36091",
                "_lon": "-1.79503"
              },
              {
                "_lat": "43.3609",
                "_lon": "-1.795"
              },
              {
                "_lat": "43.3609",
                "_lon": "-1.79498"
              },
              {
                "_lat": "43.36089",
                "_lon": "-1.79495"
              },
              {
                "_lat": "43.36089",
                "_lon": "-1.79492"
              },
              {
                "_lat": "43.36089",
                "_lon": "-1.79489"
              },
              {
                "_lat": "43.36089",
                "_lon": "-1.79487"
              },
              {
                "_lat": "43.3609",
                "_lon": "-1.79484"
              },
              {
                "_lat": "43.3609",
                "_lon": "-1.79481"
              },
              {
                "_lat": "43.36091",
                "_lon": "-1.79479"
              },
              {
                "_lat": "43.36092",
                "_lon": "-1.79476"
              },
              {
                "_lat": "43.36093",
                "_lon": "-1.79474"
              },
              {
                "_lat": "43.36094",
                "_lon": "-1.79471"
              },
              {
                "_lat": "43.36096",
                "_lon": "-1.79469"
              },
              {
                "_lat": "43.36097",
                "_lon": "-1.79468"
              },
              {
                "_lat": "43.36099",
                "_lon": "-1.79466"
              },
              {
                "_lat": "43.361",
                "_lon": "-1.79464"
              },
              {
                "_lat": "43.36104",
                "_lon": "-1.79463"
              },
              {
                "_lat": "43.36101",
                "_lon": "-1.79455"
              },
              {
                "_lat": "43.361",
                "_lon": "-1.79449"
              },
              {
                "_lat": "43.36099",
                "_lon": "-1.79443"
              },
              {
                "_lat": "43.36098",
                "_lon": "-1.79438"
              },
              {
                "_lat": "43.36099",
                "_lon": "-1.79434"
              },
              {
                "_lat": "43.361",
                "_lon": "-1.79425"
              },
              {
                "_lat": "43.36118",
                "_lon": "-1.7935"
              },
              {
                "_lat": "43.3613",
                "_lon": "-1.79291"
              },
              {
                "_lat": "43.36128",
                "_lon": "-1.79239"
              },
              {
                "_lat": "43.36126",
                "_lon": "-1.79215"
              },
              {
                "_lat": "43.36124",
                "_lon": "-1.79187"
              },
              {
                "_lat": "43.36122",
                "_lon": "-1.79173"
              },
              {
                "_lat": "43.36121",
                "_lon": "-1.79165"
              },
              {
                "_lat": "43.36112",
                "_lon": "-1.79083"
              },
              {
                "_lat": "43.36107",
                "_lon": "-1.79054"
              },
              {
                "_lat": "43.36107",
                "_lon": "-1.79054"
              },
              {
                "_lat": "43.36106",
                "_lon": "-1.79054"
              },
              {
                "_lat": "43.36106",
                "_lon": "-1.79055"
              },
              {
                "_lat": "43.36105",
                "_lon": "-1.79055"
              },
              {
                "_lat": "43.36104",
                "_lon": "-1.79056"
              },
              {
                "_lat": "43.36103",
                "_lon": "-1.79056"
              },
              {
                "_lat": "43.36102",
                "_lon": "-1.79056"
              },
              {
                "_lat": "43.36101",
                "_lon": "-1.79056"
              },
              {
                "_lat": "43.36101",
                "_lon": "-1.79057"
              },
              {
                "_lat": "43.361",
                "_lon": "-1.79057"
              },
              {
                "_lat": "43.36099",
                "_lon": "-1.79057"
              },
              {
                "_lat": "43.36099",
                "_lon": "-1.79056"
              },
              {
                "_lat": "43.36098",
                "_lon": "-1.79056"
              },
              {
                "_lat": "43.36097",
                "_lon": "-1.79056"
              },
              {
                "_lat": "43.36096",
                "_lon": "-1.79056"
              },
              {
                "_lat": "43.36095",
                "_lon": "-1.79055"
              },
              {
                "_lat": "43.36094",
                "_lon": "-1.79054"
              },
              {
                "_lat": "43.36093",
                "_lon": "-1.79053"
              },
              {
                "_lat": "43.36092",
                "_lon": "-1.79053"
              },
              {
                "_lat": "43.36092",
                "_lon": "-1.79052"
              },
              {
                "_lat": "43.36091",
                "_lon": "-1.79052"
              },
              {
                "_lat": "43.36091",
                "_lon": "-1.79051"
              },
              {
                "_lat": "43.36091",
                "_lon": "-1.7905"
              },
              {
                "_lat": "43.3609",
                "_lon": "-1.79049"
              },
              {
                "_lat": "43.36089",
                "_lon": "-1.79048"
              },
              {
                "_lat": "43.36089",
                "_lon": "-1.79047"
              },
              {
                "_lat": "43.36089",
                "_lon": "-1.79046"
              },
              {
                "_lat": "43.36089",
                "_lon": "-1.79045"
              },
              {
                "_lat": "43.36088",
                "_lon": "-1.79044"
              },
              {
                "_lat": "43.36088",
                "_lon": "-1.79043"
              },
              {
                "_lat": "43.36088",
                "_lon": "-1.79042"
              },
              {
                "_lat": "43.36088",
                "_lon": "-1.79041"
              },
              {
                "_lat": "43.36088",
                "_lon": "-1.7904"
              }
        ]
    
    }

}